fuzzercorn/__init__.py
fuzzercorn/fuzzercorn.py
fuzzercorn/include/FuzzerCorn.h
fuzzercorn/lib/libfuzzercorn.so
fuzzercorn-0.0.1.dist-info/RECORD
fuzzercorn-0.0.1.dist-info/top_level.txt
fuzzercorn-0.0.1.dist-info/METADATA
fuzzercorn-0.0.1.dist-info/WHEEL
fuzzercorn.libs/libunicorn-5b5c54e6.so.2
fuzzercorn.libs/libfuzzer-aad30c39.so
