Metadata-Version: 2.1
Name: fuzzercorn
Version: 0.0.1
Summary: Libfuzzer bindings for Unicorn..
Home-page: https://github.com/wtdcode/fuzzercorn
Author: Lazymio
Author-email: mio@lazym.io
License: UNKNOWN
Platform: UNKNOWN
Classifier: Programming Language :: Python :: 3
Requires: ctypes
Provides: fuzzercorn
Requires-Dist: unicorn (>=2.0.0rc5)
